all/__init__.py
all/agents/__init__.py
all/agents/_agent.py
all/agents/_multiagent.py
all/agents/_parallel_agent.py
all/agents/a2c.py
all/agents/c51.py
all/agents/ddpg.py
all/agents/ddqn.py
all/agents/dqn.py
all/agents/independent.py
all/agents/ppo.py
all/agents/rainbow.py
all/agents/sac.py
all/agents/vac.py
all/agents/vpg.py
all/agents/vqn.py
all/agents/vsarsa.py
all/approximation/__init__.py
all/approximation/approximation.py
all/approximation/feature_network.py
all/approximation/feature_network_test.py
all/approximation/identity.py
all/approximation/identity_test.py
all/approximation/q_continuous.py
all/approximation/q_dist.py
all/approximation/q_dist_test.py
all/approximation/q_network.py
all/approximation/q_network_test.py
all/approximation/v_network.py
all/approximation/v_network_test.py
all/approximation/checkpointer/__init__.py
all/approximation/target/__init__.py
all/approximation/target/abstract.py
all/approximation/target/fixed.py
all/approximation/target/polyak.py
all/approximation/target/trivial.py
all/bodies/__init__.py
all/bodies/_body.py
all/bodies/atari.py
all/bodies/rewards.py
all/bodies/time.py
all/bodies/time_test.py
all/bodies/vision.py
all/core/__init__.py
all/core/state.py
all/core/state_test.py
all/environments/__init__.py
all/environments/_environment.py
all/environments/_multiagent_environment.py
all/environments/_vector_environment.py
all/environments/atari.py
all/environments/atari_test.py
all/environments/atari_wrappers.py
all/environments/duplicate_env.py
all/environments/duplicate_env_test.py
all/environments/gym.py
all/environments/gym_test.py
all/environments/gym_wrappers.py
all/environments/gym_wrappers_test.py
all/environments/mujoco.py
all/environments/mujoco_test.py
all/environments/multiagent_atari.py
all/environments/multiagent_atari_test.py
all/environments/multiagent_pettingzoo.py
all/environments/multiagent_pettingzoo_test.py
all/environments/pybullet.py
all/environments/pybullet_test.py
all/environments/vector_env.py
autonomous_learning_library-0.9.1.dist-info/LICENSE
autonomous_learning_library-0.9.1.dist-info/METADATA
autonomous_learning_library-0.9.1.dist-info/WHEEL
autonomous_learning_library-0.9.1.dist-info/entry_points.txt
autonomous_learning_library-0.9.1.dist-info/top_level.txt
autonomous_learning_library-0.9.1.dist-info/RECORD
